zope.error-5.0-py3.11-nspkg.pth
zope/error/__init__.py
zope/error/configure.zcml
zope/error/error.py
zope/error/interfaces.py
zope/error/tests.py
zope.error-5.0.dist-info/LICENSE.txt
zope.error-5.0.dist-info/METADATA
zope.error-5.0.dist-info/WHEEL
zope.error-5.0.dist-info/namespace_packages.txt
zope.error-5.0.dist-info/top_level.txt
zope.error-5.0.dist-info/RECORD
